mdorrst/__init__.py
mdorrst/mdorrst.py
mdorrst-0.4.0.dist-info/DESCRIPTION.rst
mdorrst-0.4.0.dist-info/METADATA
mdorrst-0.4.0.dist-info/RECORD
mdorrst-0.4.0.dist-info/WHEEL
mdorrst-0.4.0.dist-info/entry_points.txt
mdorrst-0.4.0.dist-info/metadata.json
mdorrst-0.4.0.dist-info/top_level.txt
