Metadata-Version: 2.0
Name: mdorrst
Version: 0.4.0
Summary: Tell appart Markdown and reStructuredText.
Home-page: https://github.com/JulienPalard/mdorrst
Author: Julien Palard
Author-email: julien@palard.fr
License: MIT license
Keywords: mdorrst
Platform: UNKNOWN
Classifier: Development Status :: 4 - Beta
Classifier: Intended Audience :: Developers
Classifier: License :: OSI Approved :: MIT License
Classifier: Natural Language :: English
Classifier: Programming Language :: Python :: 2.7
Classifier: Programming Language :: Python :: 3
Classifier: Programming Language :: Python :: 3.3
Classifier: Programming Language :: Python :: 3.4
Classifier: Programming Language :: Python :: 3.5
